ctwther/__init__.py
ctwther/example.py
ctwther/wea.py
ctweather-0.0.7.dist-info/METADATA
ctweather-0.0.7.dist-info/WHEEL
ctweather-0.0.7.dist-info/top_level.txt
ctweather-0.0.7.dist-info/RECORD
