Metadata-Version: 2.1
Name: ctweather
Version: 0.0.7
Summary: get weather information of cities
Home-page: https://github.com/dldbcosmos/ctweather
Author: yakilee
Author-email: yakilee@gmail.com
Project-URL: Bug Tracker, https://github.com/dldbcosmos/ctweather/issues
Classifier: Programming Language :: Python :: 3
Classifier: License :: OSI Approved :: MIT License
Classifier: Operating System :: OS Independent
Requires-Python: >=3.6
